txgz/__init__.py
txgz/file.py
txgzfunc-0.0.7.dist-info/LICENSE
txgzfunc-0.0.7.dist-info/METADATA
txgzfunc-0.0.7.dist-info/WHEEL
txgzfunc-0.0.7.dist-info/top_level.txt
txgzfunc-0.0.7.dist-info/RECORD
