Metadata-Version: 2.1
Name: txgzfunc
Version: 0.0.7
Summary: tools
Home-page: https://github.com/txgzlyy/txgz_func
Author: txgz
Author-email: 975663670@qq.com
License: UNKNOWN
Platform: UNKNOWN
Classifier: Programming Language :: Python :: 3
Classifier: License :: OSI Approved :: MIT License
Classifier: Operating System :: OS Independent
Requires-Python: >=3.6
Requires-Dist: python-docx
Requires-Dist: pypiwin32
Requires-Dist: zhon
Requires-Dist: pdfminer3k
